castero/__init__.py
castero/__main__.py
castero/config.py
castero/constants.py
castero/database.py
castero/datafile.py
castero/display.py
castero/downloadqueue.py
castero/episode.py
castero/feed.py
castero/helpers.py
castero/menu.py
castero/net.py
castero/perspective.py
castero/player.py
castero/queue.py
castero/subscriptions.py
castero/menus/chronomenu.py
castero/menus/downloadedmenu.py
castero/menus/episodemenu.py
castero/menus/feedmenu.py
castero/menus/queuemenu.py
castero/perspectives/chronoperspective.py
castero/perspectives/downloadedperspective.py
castero/perspectives/primaryperspective.py
castero/perspectives/queueperspective.py
castero/perspectives/simpleperspective.py
castero/players/mpvplayer.py
castero/players/vlcplayer.py
castero/templates/castero.conf
castero/templates/migrations/001-initial.sql
castero/templates/migrations/002-played.sql
castero/templates/migrations/003-queue.sql
castero/templates/migrations/004-progress.sql
castero-0.9.5.dist-info/LICENSE.txt
castero-0.9.5.dist-info/METADATA
castero-0.9.5.dist-info/WHEEL
castero-0.9.5.dist-info/entry_points.txt
castero-0.9.5.dist-info/top_level.txt
castero-0.9.5.dist-info/RECORD
