Metadata-Version: 2.1
Name: castero
Version: 0.9.5
Summary: A TUI podcast client for the terminal
Home-page: https://github.com/xgi/castero
Author: xgi
Author-email: xgi@faltro.com
License: MIT License
Keywords: podcast commandline terminal tui curses
Platform: UNKNOWN
Classifier: Intended Audience :: End Users/Desktop
Classifier: Environment :: Console :: Curses
Classifier: Programming Language :: Python :: 3
Classifier: Programming Language :: Python :: 3.6
Classifier: Programming Language :: Python :: 3.7
Classifier: License :: OSI Approved :: MIT License
Classifier: Topic :: Terminals
Requires-Python: >=3
Requires-Dist: beautifulsoup4
Requires-Dist: cjkwrap
Requires-Dist: grequests
Requires-Dist: lxml
Requires-Dist: python-mpv
Requires-Dist: python-vlc
Requires-Dist: pytz
Requires-Dist: requests
Provides-Extra: test
Requires-Dist: coverage ; extra == 'test'
Requires-Dist: pytest ; extra == 'test'
